common/CreateConfig.py
common/__init__.py
common/config/__init__.py
common/config/config_data.py
common/config/create.py
common/config/creation_config.py
fun/__init__.py
fun/data_class_port.py
fun/json_execute.py
fun/mysql_execute.py
fun/redis_execute.py
fun/sqlite_execute.py
XDataExecute-0.1.5.dist-info/LICENSE.txt
XDataExecute-0.1.5.dist-info/METADATA
XDataExecute-0.1.5.dist-info/WHEEL
XDataExecute-0.1.5.dist-info/entry_points.txt
XDataExecute-0.1.5.dist-info/top_level.txt
XDataExecute-0.1.5.dist-info/RECORD
